gsadz/__init__.py
gsadz/parse_data.py
gsadz/pt/SentiLex-flex-PT02.txt
gsadz/pt/SentiLex-lem-PT02.txt
gsadz/pt/booster.txt
gsadz/pt/negate.txt
gsadz-0.1.0.dist-info/entry_points.txt
gsadz-0.1.0.dist-info/WHEEL
gsadz-0.1.0.dist-info/METADATA
gsadz-0.1.0.dist-info/RECORD
