Metadata-Version: 2.1
Name: gsadz
Version: 0.1.0
Summary: NAME
Keywords: gsadz,sentiment analysis,SentiLex-PT,spacy
Author-email: duarte <duarte.g.parente@gmail.com>, goncalo <goncalocp02@gmail.com>, topzN <jose.moreira.um@gmail.com>
Requires-Python: >=3.8
Classifier: License :: OSI Approved :: MIT License
Requires-Dist: spacy>=3.7.4
Requires-Dist: jjcli
Project-URL: Source, https://github.com/duarteparente/gsadz
